freqtrade/__init__.py
freqtrade/__main__.py
freqtrade/constants.py
freqtrade/exceptions.py
freqtrade/freqtradebot.py
freqtrade/main.py
freqtrade/misc.py
freqtrade/wallets.py
freqtrade/worker.py
freqtrade/commands/__init__.py
freqtrade/commands/analyze_commands.py
freqtrade/commands/arguments.py
freqtrade/commands/build_config_commands.py
freqtrade/commands/cli_options.py
freqtrade/commands/data_commands.py
freqtrade/commands/db_commands.py
freqtrade/commands/deploy_commands.py
freqtrade/commands/deploy_ui.py
freqtrade/commands/hyperopt_commands.py
freqtrade/commands/list_commands.py
freqtrade/commands/optimize_commands.py
freqtrade/commands/pairlist_commands.py
freqtrade/commands/plot_commands.py
freqtrade/commands/strategy_utils_commands.py
freqtrade/commands/trade_commands.py
freqtrade/commands/webserver_commands.py
freqtrade/config_schema/__init__.py
freqtrade/config_schema/config_schema.py
freqtrade/configuration/__init__.py
freqtrade/configuration/config_secrets.py
freqtrade/configuration/config_setup.py
freqtrade/configuration/config_validation.py
freqtrade/configuration/configuration.py
freqtrade/configuration/deploy_config.py
freqtrade/configuration/deprecated_settings.py
freqtrade/configuration/detect_environment.py
freqtrade/configuration/directory_operations.py
freqtrade/configuration/environment_vars.py
freqtrade/configuration/load_config.py
freqtrade/configuration/timerange.py
freqtrade/data/__init__.py
freqtrade/data/dataprovider.py
freqtrade/data/entryexitanalysis.py
freqtrade/data/metrics.py
freqtrade/data/btanalysis/__init__.py
freqtrade/data/btanalysis/bt_fileutils.py
freqtrade/data/btanalysis/historic_precision.py
freqtrade/data/btanalysis/trade_parallelism.py
freqtrade/data/converter/__init__.py
freqtrade/data/converter/converter.py
freqtrade/data/converter/orderflow.py
freqtrade/data/converter/trade_converter.py
freqtrade/data/converter/trade_converter_kraken.py
freqtrade/data/history/__init__.py
freqtrade/data/history/history_utils.py
freqtrade-2025.11.1.dist-info/licenses/LICENSE
freqtrade-2025.11.1.dist-info/METADATA
freqtrade-2025.11.1.dist-info/WHEEL
freqtrade-2025.11.1.dist-info/entry_points.txt
freqtrade-2025.11.1.dist-info/top_level.txt
freqtrade-2025.11.1.dist-info/RECORD
