Metadata-Version: 2.4
Name: freqtrade
Version: 2025.11.1
Summary: Freqtrade - Crypto Trading Bot
Author: Freqtrade Team
Author-email: Freqtrade Team <freqtrade@protonmail.com>
License: GPLv3
Project-URL: Homepage, https://github.com/freqtrade/freqtrade
Project-URL: Documentation, https://freqtrade.io
Project-URL: Bug Tracker, https://github.com/freqtrade/freqtrade/issues
Classifier: Environment :: Console
Classifier: Intended Audience :: Science/Research
Classifier: License :: OSI Approved :: GNU General Public License v3 (GPLv3)
Classifier: Programming Language :: Python :: 3.11
Classifier: Programming Language :: Python :: 3.12
Classifier: Programming Language :: Python :: 3.13
Classifier: Operating System :: MacOS
Classifier: Operating System :: Unix
Classifier: Topic :: Office/Business :: Financial :: Investment
Requires-Python: >=3.11
License-File: LICENSE
Requires-Dist: ccxt>=4.5.4
Requires-Dist: SQLAlchemy>=2.0.6
Requires-Dist: python-telegram-bot>=20.1
Requires-Dist: humanize>=4.0.0
Requires-Dist: cachetools
Requires-Dist: requests
Requires-Dist: httpx>=0.24.1
Requires-Dist: urllib3
Requires-Dist: jsonschema
Requires-Dist: numpy<3.0,>2.0
Requires-Dist: pandas<3.0,>=2.2.0
Requires-Dist: TA-Lib<0.7
Requires-Dist: ft-pandas-ta
Requires-Dist: technical
Requires-Dist: tabulate
Requires-Dist: pycoingecko>=3.2.0
Requires-Dist: python-rapidjson
Requires-Dist: orjson
Requires-Dist: jinja2
Requires-Dist: questionary
Requires-Dist: prompt-toolkit
Requires-Dist: joblib>=1.2.0
Requires-Dist: rich
Requires-Dist: pyarrow; platform_machine != "armv7l"
Requires-Dist: fastapi
Requires-Dist: pydantic>=2.2.0
Requires-Dist: pyjwt
Requires-Dist: websockets
Requires-Dist: uvicorn
Requires-Dist: psutil
Requires-Dist: schedule
Requires-Dist: janus
Requires-Dist: ast-comments
Requires-Dist: aiofiles
Requires-Dist: aiohttp
Requires-Dist: cryptography
Requires-Dist: sdnotify
Requires-Dist: python-dateutil
Requires-Dist: pytz
Requires-Dist: packaging
Requires-Dist: freqtrade-client
Provides-Extra: plot
Requires-Dist: plotly>=4.0; extra == "plot"
Provides-Extra: hyperopt
Requires-Dist: scipy; extra == "hyperopt"
Requires-Dist: scikit-learn; extra == "hyperopt"
Requires-Dist: optuna>4.0.0; extra == "hyperopt"
Requires-Dist: cmaes; extra == "hyperopt"
Requires-Dist: filelock; extra == "hyperopt"
Provides-Extra: freqai
Requires-Dist: scikit-learn; extra == "freqai"
Requires-Dist: joblib; extra == "freqai"
Requires-Dist: catboost; platform_machine != "arm" and extra == "freqai"
Requires-Dist: lightgbm; extra == "freqai"
Requires-Dist: xgboost; extra == "freqai"
Requires-Dist: tensorboard; extra == "freqai"
Requires-Dist: datasieve>=0.1.5; extra == "freqai"
Provides-Extra: freqai-rl
Requires-Dist: torch; (sys_platform != "darwin" or platform_machine != "x86_64") and extra == "freqai-rl"
Requires-Dist: gymnasium; extra == "freqai-rl"
Requires-Dist: stable-baselines3; (sys_platform != "darwin" or platform_machine != "x86_64") and extra == "freqai-rl"
Requires-Dist: sb3-contrib; (sys_platform != "darwin" or platform_machine != "x86_64") and extra == "freqai-rl"
Requires-Dist: tqdm; extra == "freqai-rl"
Provides-Extra: develop
Requires-Dist: isort; extra == "develop"
Requires-Dist: mypy; extra == "develop"
Requires-Dist: pre-commit; extra == "develop"
Requires-Dist: pytest-asyncio; extra == "develop"
Requires-Dist: pytest-cov; extra == "develop"
Requires-Dist: pytest-mock; extra == "develop"
Requires-Dist: pytest-random-order; extra == "develop"
Requires-Dist: pytest-timeout; extra == "develop"
Requires-Dist: pytest-xdist; extra == "develop"
Requires-Dist: pytest; extra == "develop"
Requires-Dist: ruff; extra == "develop"
Requires-Dist: scipy-stubs; extra == "develop"
Requires-Dist: time-machine; extra == "develop"
Requires-Dist: types-cachetools; extra == "develop"
Requires-Dist: types-filelock; extra == "develop"
Requires-Dist: types-python-dateutil; extra == "develop"
Requires-Dist: types-requests; extra == "develop"
Requires-Dist: types-tabulate; extra == "develop"
Provides-Extra: jupyter
Requires-Dist: jupyter; extra == "jupyter"
Requires-Dist: nbstripout; extra == "jupyter"
Requires-Dist: ipykernel; extra == "jupyter"
Requires-Dist: nbconvert; extra == "jupyter"
Provides-Extra: all
Requires-Dist: freqtrade[freqai,freqai_rl,hyperopt,jupyter,plot]; extra == "all"
Provides-Extra: dev
Requires-Dist: freqtrade[all,develop]; extra == "dev"
Dynamic: license-file
